srtfilter/__init__.py
srtfilter/__main__.py
srtfilter/parse.py
srtfilter/srtfilter_cli.py
srtfilter/filters/rebreak_lines.py
srtfilter-0.3.0.dist-info/METADATA
srtfilter-0.3.0.dist-info/WHEEL
srtfilter-0.3.0.dist-info/entry_points.txt
srtfilter-0.3.0.dist-info/licenses/LICENSE.txt
srtfilter-0.3.0.dist-info/RECORD
